_pylibmpsse.so
pylibmpsse.py
mpsse.py
libmpsse-1.3.dist-info/top_level.txt
libmpsse-1.3.dist-info/RECORD
libmpsse-1.3.dist-info/metadata.json
libmpsse-1.3.dist-info/WHEEL
libmpsse-1.3.dist-info/METADATA
libmpsse-1.3.dist-info/DESCRIPTION.rst
