Metadata-Version: 2.0
Name: libmpsse
Version: 1.3
Summary: Library to interface with SPI/I2C via. FTDI
Home-page: https://github.com/devttys0/libmpsse/tree/master/docs
Author: devttys0
Author-email: UNKNOWN
License: UNKNOWN
Platform: UNKNOWN
Classifier: Intended Audience :: Developers
Classifier: Natural Language :: English
Classifier: License :: OSI Approved :: BSD License
Classifier: Programming Language :: Python
Classifier: Programming Language :: Python :: 2.7
